{
  "allOf":
  [
    {
      "title": "mc_control::fsm::EnableControllerState",
      "description": "Switch to the given controller.<br/>Outputs \"OK\" in case of success, \"Failed\" otherwise.",
      "type": "object",
      "properties":
      {
        "base": { "const": "EnableController" },
        "NextController":
        {
          "type": "string",
          "default": "",
          "description": "Controller to switch to"
        }
      },
      "required": ["base"]
    },
    {
      "$ref": "../common/State.json"
    }
  ]
}
