{
   "General" : {
      "CoMMove" : {
         "comObj" : {
            "timeout" : 10.0,
            "comOffset" : [ 0.0, 0.0, 0.0 ],
            "posThresh" : 0.005,
            "velThresh" : 0.0001
         },
         "comTask" : {
            "extraStiffness" : 4.0,
            "stiffness" : 4.0,
            "targetSpeed" : 0.003,
            "weight" : 400.0
         },
         "postureTask" : {
            "stiffness" : 0.10,
            "weight" : 10.0
         }
      },
      "ContactMove" : {
         "comObj" : {
            "timeout" : 10.0,
            "comOffset" : [ 0.0, 0.0, 0.0 ],
            "posThresh" : 0.10,
            "velThresh" : 0.001
         },
         "comTask" : {
            "extraStiffness" : 0.0,
            "stiffness" : 5.0,
            "targetSpeed" : 0.006,
            "weight" : 500.0
         },
         "contactObj" : {
            "adjustOffset" : [ 0.0, 0.0, 0.0 ],
            "adjustOriTBNWeight" : [
               0,
               0,
               0
            ],
            "adjustOriThresh" : 0,
            "adjustPosThresh" : 0,
            "adjustVelThresh" : 0,
            "posThresh" : 0.03,
            "preContactDist" : 0.05,
            "velThresh" : 0.03,
            "useComplianceTask" : false,
            "complianceVelThresh" : 0.005,
            "complianceTargetForce" : [ 0, 0, 100]
         },
         "contactTask" : {
            "collisionConf" : {
               "damping" : 0.050,
               "iDist" : 0.010,
               "sDist" : 0.0050
            },
            "linVel" : {
               "speed" : 0.08,
               "stiffness" : 1.0,
               "weight" : 10000.0
            },
            "orientation" : {
               "finalWeight" : 1000.0,
               "stiffness" : 15.0,
               "weight" : 200.0
            },
            "position" : {
               "extraStiffness" : 6.0,
               "stiffness" : 2.0,
               "targetSpeed" : 0.01,
               "weight" : 300.0
            },
            "waypointConf" : {
               "conf" : {
                  "x" : 0.10,
                  "y" : 1.0,
                  "z" : 0.90,
                  "nOff" : 0.20
               },
               "thresh" : 0.150,
               "type" : "percentWaypoint"
            }
         },
         "postureTask" : {
            "stiffness" : 2.0,
            "weight" : 10.0
         }
      },
      "GripperMove" : {
         "comObj" : {
            "timeout" : 10.0,
            "comOffset" : [ 0.0, 0.0, 0.0 ],
            "posThresh" : 0.10,
            "velThresh" : 9.899999999999999e-05
         },
         "comTask" : {
            "extraStiffness" : 0.50,
            "stiffness" : 1.0,
            "targetSpeed" : 0.00050,
            "weight" : 500.0
         },
         "contactObj" : {
            "adjustOffset" : [ 0.0, 0.0, 0.0 ],
            "adjustOriTBNWeight" : [ 1.0, 1.0, 1.0 ],
            "adjustOriThresh" : 0.10,
            "adjustPosThresh" : 0.050,
            "adjustVelThresh" : 0.020,
            "posThresh" : 0.030,
            "preContactDist" : 0.020,
            "velThresh" : 0.030,
            "gripperMoveAwayDist" : 0.0
         },
         "contactTask" : {
            "collisionConf" : {
               "damping" : 0.050,
               "iDist" : 0.010,
               "sDist" : 0.0050
            },
            "linVel" : {
               "speed" : 0.020,
               "stiffness" : 1.0,
               "weight" : 1000.0
            },
            "orientation" : {
               "finalWeight" : 1000.0,
               "stiffness" : 0.25,
               "weight" : 200.0
            },
            "position" : {
               "extraStiffness" : 1.0,
               "stiffness" : 0.25,
               "targetSpeed" : 0.00050,
               "weight" : 600.0
            },
            "waypointConf" : {
               "conf" : {
                  "x" : 0.30,
                  "y" : 0.80,
                  "z" : 0.70,
                  "nOff" : 0.20
               },
               "thresh" : 0.10,
               "type" : "percentWaypoint"
            }
         },
         "postureTask" : {
            "stiffness" : 1.0,
            "weight" : 10.0
         }
      },
      "Collisions" : {
         "autoc" : [
            {
               "body1" : "RLEG_LINK2",
               "body2" : "LLEG_LINK2",
               "collisionConf" : {
                  "damping" : 0.0,
                  "iDist" : 0.050,
                  "sDist" : 0.010
               }
            },
            {
               "body1" : "RLEG_LINK3",
               "body2" : "LLEG_LINK3",
               "collisionConf" : {
                  "damping" : 0.0,
                  "iDist" : 0.050,
                  "sDist" : 0.010
               }
            },
            {
               "body1" : "RLEG_LINK5",
               "body2" : "LLEG_LINK5",
               "collisionConf" : {
                  "damping" : 0.0,
                  "iDist" : 0.050,
                  "sDist" : 0.010
               }
            },
            {
               "body1" : "RLEG_LINK5",
               "body2" : "LLEG_LINK3",
               "collisionConf" : {
                  "damping" : 0.0,
                  "iDist" : 0.050,
                  "sDist" : 0.010
               }
            },
            {
               "body1" : "LLEG_LINK5",
               "body2" : "RLEG_LINK3",
               "collisionConf" : {
                  "damping" : 0.0,
                  "iDist" : 0.050,
                  "sDist" : 0.010
               }
            },
            {
               "body1" : "RARM_LINK6",
               "body2" : "RLEG_LINK3",
               "collisionConf" : {
                  "damping" : 0.0,
                  "iDist" : 0.10,
                  "sDist" : 0.050
               }
            },
            {
               "body1" : "RARM_LINK6",
               "body2" : "RLEG_LINK2",
               "collisionConf" : {
                  "damping" : 0.0,
                  "iDist" : 0.10,
                  "sDist" : 0.050
               }
            },
            {
               "body1" : "RARM_LINK6",
               "body2" : "RLEG_LINK3",
               "collisionConf" : {
                  "damping" : 0.0,
                  "iDist" : 0.10,
                  "sDist" : 0.050
               }
            },
            {
               "body1" : "RARM_LINK6",
               "body2" : "LLEG_LINK2",
               "collisionConf" : {
                  "damping" : 0.0,
                  "iDist" : 0.10,
                  "sDist" : 0.050
               }
            },
            {
               "body1" : "RARM_LINK6",
               "body2" : "LLEG_LINK3",
               "collisionConf" : {
                  "damping" : 0.0,
                  "iDist" : 0.10,
                  "sDist" : 0.050
               }
            },
            {
               "body1" : "RARM_LINK6",
               "body2" : "CHEST_LINK1",
               "collisionConf" : {
                  "damping" : 0.0,
                  "iDist" : 0.10,
                  "sDist" : 0.050
               }
            },
            {
               "body1" : "RARM_LINK6",
               "body2" : "BODY",
               "collisionConf" : {
                  "damping" : 0.0,
                  "iDist" : 0.10,
                  "sDist" : 0.050
               }
            }
         ],
         "robotEnv" : [
            {
               "body1" : "RARM_LINK6",
               "body2" : "stair_step2",
               "collisionConf" : {
                  "damping" : 0.0,
                  "iDist" : 0.2,
                  "sDist" : 0.1
               }
            },
            {
               "body1" : "RARM_LINK6",
               "body2" : "stair_step3",
               "collisionConf" : {
                  "damping" : 0.0,
                  "iDist" : 0.2,
                  "sDist" : 0.1
               }
            },
            {
               "body1" : "LLEG_LINK3",
               "body2" : "stair_step3",
               "collisionConf" : {
                  "damping" : 0.0,
                  "iDist" : 0.1,
                  "sDist" : 0.05
               }
            },
            {
               "body1" : "RARM_LINK6",
               "body2" : "platform",
               "collisionConf" : {
                  "damping" : 0.0,
                  "iDist" : 0.2,
                  "sDist" : 0.1
               }
            }
         ],
         "robotEnvContactFilter" : [
           {
             "surf1" : "LeftGripper",
             "surf2" : "StairLeftRung1",
             "filtered" : [
              {
                "body1" : "LARM_LINK6",
                "body2" : "stair_left_railing"
              }
             ]
           },
           {
             "surf1" : "LeftGripper",
             "surf2" : "StairLeftRung2",
             "filtered" : [
              {
                "body1" : "LARM_LINK6",
                "body2" : "stair_left_railing"
              }
             ]
           }
         ]
      }
   },
   "StepByStep" : [
      {
         "type" : "add",
         "r1Surface" : "LeftGripper",
         "r2Surface" : "StairLeftRung1",
         "contactTask" : {
            "waypointConf" : {
               "conf" : {
                  "x" : 0.15,
                  "y" : 2.5,
                  "z" : 0.6,
                  "nOff" : 0.2
               },
               "thresh" : 0.15,
               "type" : "percentWaypoint"
            }
         },
         "contactObj" : {
           "preContactDist" : 0.09
         },
         "comObj" : {
            "comOffset" : [ 0.0, 0.0, -0.0 ]
         }
      },
      {
        "type" : "add",
        "r1Surface" : "LFrontSole",
        "r2Surface" : "StairStep1",
        "contactObj" : {
          "adjustOffset" : [ 0.0, 0.05, 0.0 ],
          "adjustRPYOffset" : [ 0.0, 0.0, 0.0 ]
        }
      },
      {
        "type" : "remove",
        "r1Surface" : "RFullSole",
        "r2Surface" : "Ground",
        "comObj" : {
           "comOffset" : [ 0.025, 0.025, 0.05 ]
        }
      },
      {
        "type" : "add",
        "r1Surface" : "RFrontSole",
        "r2Surface" : "StairStep1",
        "comObj" : {
           "comOffset" : [ 0.05, 0.025, 0.0 ],
           "comAdjustOffset" : [ 0.025, 0.0, 0.0 ]
        },
        "contactObj" : {
          "adjustOffset" : [ 0.0, -0.025, 0.0 ],
          "adjustRPYOffset" : [ 0.0, 0.0, 0.0 ]
        },
        "contactTask" : {
          "waypointConf" : {
            "conf" : {
               "x" : 0.10,
               "y" : 1.0,
               "z" : 0.90,
               "nOff" : 0.20,
               "yOff" : -0.05
            },
            "thresh" : 0.150,
            "type" : "percentWaypoint"
          }
        }
      },
      {
        "type" : "remove",
        "r1Surface" : "LFrontSole",
        "r2Surface" : "StairStep1",
        "comObj" : {
           "comOffset" : [ -0.025, -0.025, -0.05 ]
        },
        "postureTask" : {
           "stiffness" : 1,
           "weight" : 10000.0
        }
      },
      {
        "type" : "add",
        "r1Surface" : "LFrontSole",
        "r2Surface" : "StairStep2",
        "comObj" : {
           "comOffset" : [ 0.075, 0.0, 0.0 ],
           "comAdjustOffset" : [ 0.075, 0.0, 0.0 ]
        },
        "comTask" : {
           "extraStiffness" : 0.0,
           "stiffness" : 10.0,
           "targetSpeed" : 0.006,
           "weight" : 500.0
        },
        "contactObj" : {
          "adjustOffset" : [ 0.0, 0.1, 0.0 ],
          "adjustRPYOffset" : [ 0.0, 0.0, 0.0 ]
        },
        "contactTask" : {
            "position" : {
               "extraStiffness" : 12.0,
               "stiffness" : 6.0,
               "targetSpeed" : 0.01,
               "weight" : 300.0
            },
           "waypointConf" : {
              "conf" : {
                 "x" : 0.0,
                 "y" : 1.0,
                 "z" : 0.9,
                 "nOff" : 0.2,
                 "yOff" : 0.05
              },
              "thresh" : 0.15,
              "type" : "percentWaypoint"
           }
        }
      },
      {
        "type" : "remove",
        "r1Surface" : "RFrontSole",
        "r2Surface" : "StairStep1",
        "comObj" : {
           "comOffset" : [ 0.025, 0.0, 0.0 ]
        }
      },
      {
        "type" : "add",
        "r1Surface" : "RFrontSole",
        "r2Surface" : "StairStep2",
        "comObj" : {
           "comOffset" : [ 0.05, 0.0, 0.0 ],
           "comAdjustOffset" : [ 0.0, 0.0, 0.0 ]
        },
        "comTask" : {
           "extraStiffness" : 5.0,
           "stiffness" : 5.0,
           "targetSpeed" : 0.006,
           "weight" : 500.0
        },
        "contactObj" : {
          "adjustOffset" : [ 0.0, 0.0, 0.0 ],
          "adjustRPYOffset" : [ 0.0, 0.0, 0.0 ]
        },
        "contactTask" : {
            "position" : {
               "extraStiffness" : 6.0,
               "stiffness" : 2.0,
               "targetSpeed" : 0.01,
               "weight" : 300.0
            },
           "waypointConf" : {
              "conf" : {
                 "x" : 0.10,
                 "y" : 1.0,
                 "z" : 0.9,
                 "nOff" : 0.2,
                 "yOff" : -0.05
              },
              "thresh" : 0.15,
              "type" : "percentWaypoint"
           }
        }
      },
      {
        "type" : "add",
        "r1Surface" : "RightFingers",
        "r2Surface" : "Platform",
        "contactObj" : {
           "posThresh" : 0.03,
           "preContactDist" : 0.1,
           "velThresh" : 0.03,
           "useComplianceTask" : false,
           "complianceVelThresh" : 0.005,
           "complianceTargetForce" : [ 0, 0, 30]
        },
        "contactTask" : {
          "position" : {
             "targetSpeed" : 0.001
          },
          "waypointConf" : {
             "skip" : 1
          }
        },
        "comObj" : {
           "comOffset" : [ -0.02, 0.0, 0.0 ]
        }
      },
      {
        "type" : "remove",
        "r1Surface" : "LeftGripper",
        "r2Surface" : "StairLeftRung1",
        "comObj" : {
           "comOffset" : [ 0.0, -0.05, -0.05 ]
        }
      },
      {
         "type" : "add",
         "r1Surface" : "LeftGripper",
         "r2Surface" : "StairLeftRung2",
         "contactTask" : {
           "waypointConf" : {
              "skip" : 1
           }
         },
         "contactObj" : {
           "preContactDist" : 0,
           "adjustOffset" : [-0.03, 0.0, -0.024]
         },
         "comTask" : {
            "extraStiffness" : 1.0,
            "stiffness" : 5.0,
            "targetSpeed" : 0.00050,
            "weight" : 500.0
         },
         "comObj" : {
            "comOffset" : [ 0.025, -0.05, -0.05 ]
         }
      },
      {
        "type" : "remove",
        "r1Surface" : "LFrontSole",
        "r2Surface" : "StairStep2",
        "comObj" : {
           "comOffset" : [ 0.0, 0.1, 0.0 ]
        }
      },
      {
        "type" : "remove",
        "r1Surface" : "RFrontSole",
        "r2Surface" : "StairStep2",
        "comObj" : {
           "comOffset" : [ -0.05, 0.0, 0.0 ]
        }
      }
   ]
}
